{
  "mask": "sr",
  "version": "1.0.1",
  "lib": "react-native-white-label",
  "maskConfig": {
    "mask": "sr",
    "appName": "chanaka",
    "dirCopy": [
      {
        "sourceDri": "./wl-assets",
        "destinationDri": "./abc",
        "overwrite": true
      },
      {
        "sourceDri": "./wl-assets",
        "destinationDri": "./abcd",
        "overwrite": false
      },
      {
        "sourceDri": "./wl-assets",
        "destinationDri": "./abcde"
      }
    ]
  },
  "wlConfigLastEditedTime": 1572936635972,
  "lockedTime": 1572937976447,
  "metroConfig": {
    "resolver": {
      "sourceExts": [
        "sr.js",
        "js",
        "sr.json",
        "json",
        "sr.ts",
        "ts",
        "sr.tsx",
        "tsx"
      ]
    }
  },
  "lastKnownAssetStatString": "[[{\"dir\":\"wl-assets/a.ue.js\",\"modifiedTime\":\"2019-11-04T10:09:01.463Z\"},{\"dir\":\"wl-assets/sssss.sjs.ksks.ksks.android.js\",\"modifiedTime\":\"2019-11-05T04:23:03.609Z\"},[{\"dir\":\"wl-assets/test/de.sr.js\",\"modifiedTime\":\"2019-11-04T12:26:50.619Z\"},{\"dir\":\"wl-assets/test/w.js\",\"modifiedTime\":\"2019-11-04T12:26:59.859Z\"}]],[{\"dir\":\"wl-assets/a.ue.js\",\"modifiedTime\":\"2019-11-04T10:09:01.463Z\"},{\"dir\":\"wl-assets/sssss.sjs.ksks.ksks.android.js\",\"modifiedTime\":\"2019-11-05T04:23:03.609Z\"},[{\"dir\":\"wl-assets/test/de.sr.js\",\"modifiedTime\":\"2019-11-04T12:26:50.619Z\"},{\"dir\":\"wl-assets/test/w.js\",\"modifiedTime\":\"2019-11-04T12:26:59.859Z\"}]],[{\"dir\":\"wl-assets/a.ue.js\",\"modifiedTime\":\"2019-11-04T10:09:01.463Z\"},{\"dir\":\"wl-assets/sssss.sjs.ksks.ksks.android.js\",\"modifiedTime\":\"2019-11-05T04:23:03.609Z\"},[{\"dir\":\"wl-assets/test/de.sr.js\",\"modifiedTime\":\"2019-11-04T12:26:50.619Z\"},{\"dir\":\"wl-assets/test/w.js\",\"modifiedTime\":\"2019-11-04T12:26:59.859Z\"}]]]"
}
